corrupt_tta/__init__.py
corrupt_tta/corruptions.py
corrupt_tta/assets/frost/frost1.png
corrupt_tta/assets/frost/frost2.png
corrupt_tta/assets/frost/frost3.png
corrupt_tta/assets/frost/frost4.jpg
corrupt_tta/assets/frost/frost5.jpg
corrupt_tta/assets/frost/frost6.jpg
corrupt_tta-0.1.5.dist-info/METADATA
corrupt_tta-0.1.5.dist-info/WHEEL
corrupt_tta-0.1.5.dist-info/top_level.txt
corrupt_tta-0.1.5.dist-info/RECORD
