Metadata-Version: 2.4
Name: corrupt_tta
Version: 0.1.5
Summary: A modernized library for image corruptions based on ImageNet-C
Author-email: Manus AI <support@manus.im>
License-Expression: MIT
Project-URL: Homepage, https://github.com/YashM8/robustness/tree/modernize-corruptions
Project-URL: Repository, https://github.com/YashM8/robustness/tree/modernize-corruptions
Classifier: Programming Language :: Python :: 3
Classifier: Operating System :: OS Independent
Classifier: Topic :: Scientific/Engineering :: Image Processing
Classifier: Topic :: Scientific/Engineering :: Artificial Intelligence
Requires-Python: >=3.8
Requires-Dist: numpy
Requires-Dist: opencv-python
Requires-Dist: pillow
Requires-Dist: scipy
Requires-Dist: scikit-image
